{"_059": {"attitudeOfFriend": "ambivalentFriend", "attitude": "liberal", "transiency": "asLongAsEligible", "group": "A", "education": "NA", "occupation": "NA"}, "_265": {"attitudeOfFriend": "ambivalentFriend", "attitude": "liberal", "transiency": "untilBetterPlace", "group": "A", "education": "NA", "occupation": "NA"}, "_264": {"attitudeOfFriend": "liberalFriend", "attitude": "liberal", "transiency": "permanent", "group": "A", "education": "gradeSchoolOrLess", "occupation": "whiteColorSkilled"}, "_267": {"attitudeOfFriend": "NA", "attitude": "NA", "transiency": "asLongAsEligible", "group": "B", "education": "NA", "occupation": "NA"}, "_266": {"attitudeOfFriend": "NA", "attitude": "NA", "transiency": "NA", "group": "A", "education": "NA", "occupation": "NA"}, "_261": {"attitudeOfFriend": "NA", "attitude": "NA", "transiency": "asLongAsEligible", "group": "A", "education": "NA", "occupation": "NA"}, "_260": {"attitudeOfFriend": "liberalFriend", "attitude": "liberal", "transiency": "untilOwnHome", "group": "A", "education": "gradeSchoolOrLess", "occupation": "semiSkilled"}, "_263": {"attitudeOfFriend": "liberalFriend", "attitude": "liberal", "transiency": "neverThoughtAboutIt", "group": "B", "education": "highSchoolGraduate", "occupation": "unskilledDomesticPersonalService"}, "_262": {"attitudeOfFriend": "liberalFriend", "attitude": "liberal", "transiency": "neverThoughtAboutIt", "group": "B", "education": "someHighSchool", "occupation": "unskilledDomesticPersonalService"}, "_346": {"attitudeOfFriend": "liberalFriend", "attitude": "liberal", "transiency": "asLongAsEligible", "group": "B", "education": "highSchoolGraduate", "occupation": "semiSkilled"}, "_347": {"attitudeOfFriend": "NA", "attitude": "NA", "transiency": "neverThoughtAboutIt", "group": "A", "education": "someHighSchool", "occupation": "semiSkilled"}, "_344": {"attitudeOfFriend": "NA", "attitude": "NA", "transiency": "NA", "group": "A", "education": "gradeSchoolOrLess", "occupation": "unskilledDomesticPersonalService"}, "_345": {"attitudeOfFriend": "liberalFriend", "attitude": "ambivalent", "transiency": "asLongAsEligible", "group": "B", "education": "NA", "occupation": "NA"}, "_269": {"attitudeOfFriend": "liberalFriend", "attitude": "ambivalent", "transiency": "NA", "group": "A", "education": "gradeSchoolOrLess", "occupation": "unskilledDomesticPersonalService"}, "_268": {"attitudeOfFriend": "NA", "attitude": "NA", "transiency": "NA", "group": "B", "education": "gradeSchoolOrLess", "occupation": "unskilledDomesticPersonalService"}, "_340": {"attitudeOfFriend": "NA", "attitude": "NA", "transiency": "neverThoughtAboutIt", "group": "A", "education": "gradeSchoolOrLess", "occupation": "whiteColorSkilled"}, "_341": {"attitudeOfFriend": "liberalFriend", "attitude": "liberal", "transiency": "neverThoughtAboutIt", "group": "B", "education": "gradeSchoolOrLess", "occupation": "unskilledDomesticPersonalService"}, "_381": {"attitudeOfFriend": "NA", "attitude": "NA", "transiency": "NA", "group": "B", "education": "NA", "occupation": "NA"}, "_418": {"attitudeOfFriend": "liberalFriend", "attitude": "liberal", "transiency": "untilOwnHome", "group": "A", "education": "someHighSchool", "occupation": "unskilledDomesticPersonalService"}, "_419": {"attitudeOfFriend": "NA", "attitude": "NA", "transiency": "asLongAsEligible", "group": "A", "education": "NA", "occupation": "NA"}, "_412": {"attitudeOfFriend": "NA", "attitude": "NA", "transiency": "asLongAsEligible", "group": "B", "education": "NA", "occupation": "NA"}, "_413": {"attitudeOfFriend": "NA", "attitude": "NA", "transiency": "untilOwnHome", "group": "A", "education": "NA", "occupation": "NA"}, "_410": {"attitudeOfFriend": "NA", "attitude": "NA", "transiency": "permanent", "group": "B", "education": "gradeSchoolOrLess", "occupation": "unskilledDomesticPersonalService"}, "_411": {"attitudeOfFriend": "liberalFriend", "attitude": "liberal", "transiency": "neverThoughtAboutIt", "group": "B", "education": "gradeSchoolOrLess", "occupation": "unskilledDomesticPersonalService"}, "_416": {"attitudeOfFriend": "liberalFriend", "attitude": "liberal", "transiency": "asLongAsEligible", "group": "A", "education": "someHighSchool", "occupation": "unskilledDomesticPersonalService"}, "_417": {"attitudeOfFriend": "NA", "attitude": "NA", "transiency": "NA", "group": "B", "education": "highSchoolGraduate", "occupation": "unskilledDomesticPersonalService"}, "_414": {"attitudeOfFriend": "NA", "attitude": "NA", "transiency": "asLongAsEligible", "group": "B", "education": "NA", "occupation": "NA"}, "_415": {"attitudeOfFriend": "liberalFriend", "attitude": "liberal", "transiency": "permanent", "group": "A", "education": "someHighSchool", "occupation": "unskilledDomesticPersonalService"}, "_388": {"attitudeOfFriend": "liberalFriend", "attitude": "liberal", "transiency": "neverThoughtAboutIt", "group": "A", "education": "NA", "occupation": "NA"}, "_193": {"attitudeOfFriend": "NA", "attitude": "NA", "transiency": "NA", "group": "A", "education": "NA", "occupation": "NA"}, "_192": {"attitudeOfFriend": "liberalFriend", "attitude": "liberal", "transiency": "NA", "group": "B", "education": "gradeSchoolOrLess", "occupation": "whiteColorSkilled"}, "_191": {"attitudeOfFriend": "liberalFriend", "attitude": "liberal", "transiency": "NA", "group": "B", "education": "NA", "occupation": "NA"}, "_190": {"attitudeOfFriend": "NA", "attitude": "NA", "transiency": "asLongAsEligible", "group": "A", "education": "NA", "occupation": "NA"}, "_197": {"attitudeOfFriend": "NA", "attitude": "NA", "transiency": "asLongAsEligible", "group": "B", "education": "NA", "occupation": "NA"}, "_196": {"attitudeOfFriend": "NA", "attitude": "NA", "transiency": "NA", "group": "B", "education": "NA", "occupation": "NA"}, "_195": {"attitudeOfFriend": "liberalFriend", "attitude": "liberal", "transiency": "NA", "group": "B", "education": "highSchoolGraduate", "occupation": "semiSkilled"}, "_194": {"attitudeOfFriend": "liberalFriend", "attitude": "liberal", "transiency": "NA", "group": "A", "education": "gradeSchoolOrLess", "occupation": "whiteColorSkilled"}, "_199": {"attitudeOfFriend": "ambivalentFriend", "attitude": "liberal", "transiency": "NA", "group": "A", "education": "NA", "occupation": "NA"}, "_198": {"attitudeOfFriend": "NA", "attitude": "NA", "transiency": "neverThoughtAboutIt", "group": "A", "education": "gradeSchoolOrLess", "occupation": "unskilledDomesticPersonalService"}, "_298": {"attitudeOfFriend": "NA", "attitude": "NA", "transiency": "untilBetterPlace", "group": "B", "education": "gradeSchoolOrLess", "occupation": "unskilledDomesticPersonalService"}, "_299": {"attitudeOfFriend": "liberalFriend", "attitude": "liberal", "transiency": "NA", "group": "B", "education": "gradeSchoolOrLess", "occupation": "unskilledDomesticPersonalService"}, "_290": {"attitudeOfFriend": "NA", "attitude": "NA", "transiency": "neverThoughtAboutIt", "group": "A", "education": "NA", "occupation": "NA"}, "_291": {"attitudeOfFriend": "NA", "attitude": "NA", "transiency": "permanent", "group": "B", "education": "NA", "occupation": "NA"}, "_292": {"attitudeOfFriend": "NA", "attitude": "NA", "transiency": "untilOwnHome", "group": "A", "education": "someHighSchool", "occupation": "unskilledDomesticPersonalService"}, "_293": {"attitudeOfFriend": "NA", "attitude": "NA", "transiency": "permanent", "group": "B", "education": "someHighSchool", "occupation": "unskilledDomesticPersonalService"}, "_294": {"attitudeOfFriend": "liberalFriend", "attitude": "liberal", "transiency": "permanent", "group": "B", "education": "NA", "occupation": "NA"}, "_295": {"attitudeOfFriend": "liberalFriend", "attitude": "ambivalent", "transiency": "neverThoughtAboutIt", "group": "B", "education": "NA", "occupation": "NA"}, "_296": {"attitudeOfFriend": "liberalFriend", "attitude": "liberal", "transiency": "asLongAsEligible", "group": "B", "education": "someHighSchool", "occupation": "semiSkilled"}, "_297": {"attitudeOfFriend": "NA", "attitude": "NA", "transiency": "asLongAsEligible", "group": "B", "education": "someHighSchool", "occupation": "unskilledDomesticPersonalService"}, "_489": {"attitudeOfFriend": "NA", "attitude": "NA", "transiency": "asLongAsEligible", "group": "B", "education": "NA", "occupation": "NA"}, "_488": {"attitudeOfFriend": "NA", "attitude": "NA", "transiency": "untilOwnHome", "group": "A", "education": "gradeSchoolOrLess", "occupation": "unskilledDomesticPersonalService"}, "_485": {"attitudeOfFriend": "ambivalentFriend", "attitude": "liberal", "transiency": "asLongAsEligible", "group": "B", "education": "NA", "occupation": "NA"}, "_484": {"attitudeOfFriend": "NA", "attitude": "NA", "transiency": "asLongAsEligible", "group": "B", "education": "NA", "occupation": "NA"}, "_487": {"attitudeOfFriend": "NA", "attitude": "NA", "transiency": "asLongAsEligible", "group": "B", "education": "someHighSchool", "occupation": "unskilledDomesticPersonalService"}, "_486": {"attitudeOfFriend": "NA", "attitude": "NA", "transiency": "permanent", "group": "A", "education": "highSchoolGraduate", "occupation": "unskilledDomesticPersonalService"}, "_481": {"attitudeOfFriend": "liberalFriend", "attitude": "liberal", "transiency": "neverThoughtAboutIt", "group": "B", "education": "NA", "occupation": "NA"}, "_480": {"attitudeOfFriend": "NA", "attitude": "NA", "transiency": "asLongAsEligible", "group": "A", "education": "someHighSchool", "occupation": "semiSkilled"}, "_483": {"attitudeOfFriend": "NA", "attitude": "NA", "transiency": "NA", "group": "A", "education": "someHighSchool", "occupation": "whiteColorSkilled"}, "_482": {"attitudeOfFriend": "NA", "attitude": "NA", "transiency": "permanent", "group": "B", "education": "gradeSchoolOrLess", "occupation": "unskilledDomesticPersonalService"}, "_126": {"attitudeOfFriend": "liberalFriend", "attitude": "liberal", "transiency": "NA", "group": "A", "education": "gradeSchoolOrLess", "occupation": "unskilledDomesticPersonalService"}, "_127": {"attitudeOfFriend": "NA", "attitude": "NA", "transiency": "permanent", "group": "A", "education": "gradeSchoolOrLess", "occupation": "unskilledDomesticPersonalService"}, "_124": {"attitudeOfFriend": "NA", "attitude": "NA", "transiency": "permanent", "group": "A", "education": "gradeSchoolOrLess", "occupation": "whiteColorSkilled"}, "_125": {"attitudeOfFriend": "liberalFriend", "attitude": "liberal", "transiency": "NA", "group": "B", "education": "someHighSchool", "occupation": "unskilledDomesticPersonalService"}, "_122": {"attitudeOfFriend": "liberalFriend", "attitude": "liberal", "transiency": "NA", "group": "A", "education": "gradeSchoolOrLess", "occupation": "unskilledDomesticPersonalService"}, "_123": {"attitudeOfFriend": "liberalFriend", "attitude": "liberal", "transiency": "asLongAsEligible", "group": "B", "education": "someHighSchool", "occupation": "semiSkilled"}, "_120": {"attitudeOfFriend": "NA", "attitude": "NA", "transiency": "asLongAsEligible", "group": "B", "education": "NA", "occupation": "NA"}, "_121": {"attitudeOfFriend": "liberalFriend", "attitude": "ambivalent", "transiency": "untilOwnHome", "group": "B", "education": "NA", "occupation": "NA"}, "_128": {"attitudeOfFriend": "NA", "attitude": "NA", "transiency": "asLongAsEligible", "group": "B", "education": "someHighSchool", "occupation": "whiteColorSkilled"}, "_129": {"attitudeOfFriend": "NA", "attitude": "NA", "transiency": "permanent", "group": "A", "education": "NA", "occupation": "NA"}, "_049": {"attitudeOfFriend": "ambivalentFriend", "attitude": "liberal", "transiency": "NA", "group": "A", "education": "someHighSchool", "occupation": "unskilledDomesticPersonalService"}, "_048": {"attitudeOfFriend": "liberalFriend", "attitude": "liberal", "transiency": "untilBetterPlace", "group": "A", "education": "NA", "occupation": "NA"}, "_045": {"attitudeOfFriend": "NA", "attitude": "NA", "transiency": "NA", "group": "A", "education": "NA", "occupation": "NA"}, "_044": {"attitudeOfFriend": "NA", "attitude": "NA", "transiency": "neverThoughtAboutIt", "group": "A", "education": "NA", "occupation": "NA"}, "_047": {"attitudeOfFriend": "liberalFriend", "attitude": "liberal", "transiency": "NA", "group": "B", "education": "gradeSchoolOrLess", "occupation": "unskilledDomesticPersonalService"}, "_046": {"attitudeOfFriend": "liberalFriend", "attitude": "liberal", "transiency": "untilBetterPlace", "group": "A", "education": "highSchoolGraduate", "occupation": "semiSkilled"}, "_041": {"attitudeOfFriend": "NA", "attitude": "NA", "transiency": "asLongAsEligible", "group": "B", "education": "NA", "occupation": "NA"}, "_040": {"attitudeOfFriend": "NA", "attitude": "NA", "transiency": "asLongAsEligible", "group": "B", "education": "gradeSchoolOrLess", "occupation": "unskilledDomesticPersonalService"}, "_043": {"attitudeOfFriend": "liberalFriend", "attitude": "liberal", "transiency": "NA", "group": "A", "education": "highSchoolGraduate", "occupation": "whiteColorSkilled"}, "_042": {"attitudeOfFriend": "NA", "attitude": "NA", "transiency": "permanent", "group": "A", "education": "highSchoolGraduate", "occupation": "whiteColorSkilled"}, "_098": {"attitudeOfFriend": "NA", "attitude": "NA", "transiency": "NA", "group": "A", "education": "NA", "occupation": "NA"}, "_312": {"attitudeOfFriend": "ambivalentFriend", "attitude": "liberal", "transiency": "asLongAsEligible", "group": "B", "education": "NA", "occupation": "NA"}, "_229": {"attitudeOfFriend": "NA", "attitude": "NA", "transiency": "untilBetterPlace", "group": "A", "education": "gradeSchoolOrLess", "occupation": "semiSkilled"}, "_228": {"attitudeOfFriend": "liberalFriend", "attitude": "liberal", "transiency": "asLongAsEligible", "group": "B", "education": "NA", "occupation": "NA"}, "_221": {"attitudeOfFriend": "NA", "attitude": "NA", "transiency": "NA", "group": "B", "education": "someHighSchool", "occupation": "whiteColorSkilled"}, "_220": {"attitudeOfFriend": "liberalFriend", "attitude": "liberal", "transiency": "neverThoughtAboutIt", "group": "A", "education": "someHighSchool", "occupation": "unskilledDomesticPersonalService"}, "_223": {"attitudeOfFriend": "liberalFriend", "attitude": "liberal", "transiency": "permanent", "group": "B", "education": "gradeSchoolOrLess", "occupation": "unskilledDomesticPersonalService"}, "_222": {"attitudeOfFriend": "NA", "attitude": "NA", "transiency": "NA", "group": "B", "education": "someHighSchool", "occupation": "semiSkilled"}, "_225": {"attitudeOfFriend": "NA", "attitude": "NA", "transiency": "untilBetterPlace", "group": "B", "education": "someHighSchool", "occupation": "unskilledDomesticPersonalService"}, "_224": {"attitudeOfFriend": "liberalFriend", "attitude": "ambivalent", "transiency": "asLongAsEligible", "group": "B", "education": "someHighSchool", "occupation": "unskilledDomesticPersonalService"}, "_227": {"attitudeOfFriend": "NA", "attitude": "NA", "transiency": "permanent", "group": "B", "education": "highSchoolGraduate", "occupation": "unskilledDomesticPersonalService"}, "_226": {"attitudeOfFriend": "NA", "attitude": "NA", "transiency": "neverThoughtAboutIt", "group": "A", "education": "NA", "occupation": "NA"}, "_458": {"attitudeOfFriend": "liberalFriend", "attitude": "ambivalent", "transiency": "NA", "group": "B", "education": "NA", "occupation": "NA"}, "_459": {"attitudeOfFriend": "NA", "attitude": "NA", "transiency": "asLongAsEligible", "group": "A", "education": "gradeSchoolOrLess", "occupation": "unskilledDomesticPersonalService"}, "_456": {"attitudeOfFriend": "NA", "attitude": "NA", "transiency": "asLongAsEligible", "group": "B", "education": "gradeSchoolOrLess", "occupation": "unskilledDomesticPersonalService"}, "_457": {"attitudeOfFriend": "liberalFriend", "attitude": "liberal", "transiency": "neverThoughtAboutIt", "group": "B", "education": "highSchoolGraduate", "occupation": "semiSkilled"}, "_454": {"attitudeOfFriend": "NA", "attitude": "NA", "transiency": "asLongAsEligible", "group": "B", "education": "NA", "occupation": "NA"}, "_455": {"attitudeOfFriend": "NA", "attitude": "NA", "transiency": "NA", "group": "B", "education": "someHighSchool", "occupation": "semiSkilled"}, "_452": {"attitudeOfFriend": "liberalFriend", "attitude": "ambivalent", "transiency": "NA", "group": "B", "education": "NA", "occupation": "NA"}, "_453": {"attitudeOfFriend": "NA", "attitude": "NA", "transiency": "untilOwnHome", "group": "A", "education": "NA", "occupation": "NA"}, "_450": {"attitudeOfFriend": "NA", "attitude": "NA", "transiency": "neverThoughtAboutIt", "group": "B", "education": "highSchoolGraduate", "occupation": "unskilledDomesticPersonalService"}, "_451": {"attitudeOfFriend": "liberalFriend", "attitude": "liberal", "transiency": "NA", "group": "A", "education": "highSchoolGraduate", "occupation": "unskilledDomesticPersonalService"}, "_315": {"attitudeOfFriend": "NA", "attitude": "NA", "transiency": "asLongAsEligible", "group": "A", "education": "NA", "occupation": "NA"}, "_314": {"attitudeOfFriend": "NA", "attitude": "NA", "transiency": "NA", "group": "B", "education": "highSchoolGraduate", "occupation": "whiteColorSkilled"}, "_317": {"attitudeOfFriend": "liberalFriend", "attitude": "liberal", "transiency": "permanent", "group": "B", "education": "NA", "occupation": "NA"}, "_316": {"attitudeOfFriend": "NA", "attitude": "NA", "transiency": "asLongAsEligible", "group": "A", "education": "NA", "occupation": "NA"}, "_311": {"attitudeOfFriend": "NA", "attitude": "NA", "transiency": "asLongAsEligible", "group": "A", "education": "NA", "occupation": "NA"}, "_310": {"attitudeOfFriend": "liberalFriend", "attitude": "liberal", "transiency": "permanent", "group": "A", "education": "someHighSchool", "occupation": "whiteColorSkilled"}, "_313": {"attitudeOfFriend": "liberalFriend", "attitude": "liberal", "transiency": "untilBetterPlace", "group": "A", "education": "gradeSchoolOrLess", "occupation": "unskilledDomesticPersonalService"}, "_099": {"attitudeOfFriend": "NA", "attitude": "NA", "transiency": "NA", "group": "B", "education": "gradeSchoolOrLess", "occupation": "unskilledDomesticPersonalService"}, "_096": {"attitudeOfFriend": "NA", "attitude": "NA", "transiency": "asLongAsEligible", "group": "B", "education": "NA", "occupation": "NA"}, "_097": {"attitudeOfFriend": "liberalFriend", "attitude": "liberal", "transiency": "NA", "group": "A", "education": "NA", "occupation": "NA"}, "_094": {"attitudeOfFriend": "NA", "attitude": "NA", "transiency": "neverThoughtAboutIt", "group": "B", "education": "highSchoolGraduate", "occupation": "unskilledDomesticPersonalService"}, "_095": {"attitudeOfFriend": "NA", "attitude": "NA", "transiency": "NA", "group": "A", "education": "gradeSchoolOrLess", "occupation": "unskilledDomesticPersonalService"}, "_092": {"attitudeOfFriend": "NA", "attitude": "NA", "transiency": "untilOwnHome", "group": "B", "education": "NA", "occupation": "NA"}, "_318": {"attitudeOfFriend": "NA", "attitude": "NA", "transiency": "neverThoughtAboutIt", "group": "B", "education": "someHighSchool", "occupation": "semiSkilled"}, "_090": {"attitudeOfFriend": "NA", "attitude": "NA", "transiency": "untilBetterPlace", "group": "B", "education": "gradeSchoolOrLess", "occupation": "unskilledDomesticPersonalService"}, "_091": {"attitudeOfFriend": "liberalFriend", "attitude": "liberal", "transiency": "asLongAsEligible", "group": "A", "education": "NA", "occupation": "NA"}, "_258": {"attitudeOfFriend": "liberalFriend", "attitude": "liberal", "transiency": "permanent", "group": "B", "education": "NA", "occupation": "NA"}, "_259": {"attitudeOfFriend": "liberalFriend", "attitude": "liberal", "transiency": "asLongAsEligible", "group": "B", "education": "gradeSchoolOrLess", "occupation": "unskilledDomesticPersonalService"}, "_254": {"attitudeOfFriend": "NA", "attitude": "NA", "transiency": "asLongAsEligible", "group": "A", "education": "someHighSchool", "occupation": "whiteColorSkilled"}, "_255": {"attitudeOfFriend": "NA", "attitude": "NA", "transiency": "NA", "group": "B", "education": "NA", "occupation": "NA"}, "_256": {"attitudeOfFriend": "liberalFriend", "attitude": "liberal", "transiency": "asLongAsEligible", "group": "A", "education": "gradeSchoolOrLess", "occupation": "unskilledDomesticPersonalService"}, "_257": {"attitudeOfFriend": "liberalFriend", "attitude": "liberal", "transiency": "untilBetterPlace", "group": "B", "education": "gradeSchoolOrLess", "occupation": "unskilledDomesticPersonalService"}, "_250": {"attitudeOfFriend": "NA", "attitude": "NA", "transiency": "asLongAsEligible", "group": "A", "education": "NA", "occupation": "NA"}, "_251": {"attitudeOfFriend": "liberalFriend", "attitude": "liberal", "transiency": "untilBetterPlace", "group": "B", "education": "gradeSchoolOrLess", "occupation": "unskilledDomesticPersonalService"}, "_252": {"attitudeOfFriend": "NA", "attitude": "NA", "transiency": "NA", "group": "B", "education": "someHighSchool", "occupation": "semiSkilled"}, "_253": {"attitudeOfFriend": "NA", "attitude": "NA", "transiency": "permanent", "group": "B", "education": "someHighSchool", "occupation": "unskilledDomesticPersonalService"}, "_348": {"attitudeOfFriend": "liberalFriend", "attitude": "liberal", "transiency": "NA", "group": "B", "education": "NA", "occupation": "NA"}, "_349": {"attitudeOfFriend": "NA", "attitude": "NA", "transiency": "untilOwnHome", "group": "B", "education": "NA", "occupation": "NA"}, "_342": {"attitudeOfFriend": "liberalFriend", "attitude": "liberal", "transiency": "NA", "group": "A", "education": "NA", "occupation": "NA"}, "_343": {"attitudeOfFriend": "NA", "attitude": "NA", "transiency": "untilBetterPlace", "group": "B", "education": "highSchoolGraduate", "occupation": "whiteColorSkilled"}, "_001": {"attitudeOfFriend": "liberalFriend", "attitude": "liberal", "transiency": "asLongAsEligible", "group": "B", "education": "highSchoolGraduate", "occupation": "semiSkilled"}, "_003": {"attitudeOfFriend": "liberalFriend", "attitude": "liberal", "transiency": "untilOwnHome", "group": "B", "education": "gradeSchoolOrLess", "occupation": "unskilledDomesticPersonalService"}, "_002": {"attitudeOfFriend": "liberalFriend", "attitude": "liberal", "transiency": "neverThoughtAboutIt", "group": "A", "education": "gradeSchoolOrLess", "occupation": "unskilledDomesticPersonalService"}, "_005": {"attitudeOfFriend": "NA", "attitude": "NA", "transiency": "NA", "group": "A", "education": "gradeSchoolOrLess", "occupation": "unskilledDomesticPersonalService"}, "_004": {"attitudeOfFriend": "NA", "attitude": "NA", "transiency": "asLongAsEligible", "group": "B", "education": "NA", "occupation": "NA"}, "_007": {"attitudeOfFriend": "liberalFriend", "attitude": "liberal", "transiency": "NA", "group": "B", "education": "highSchoolGraduate", "occupation": "whiteColorSkilled"}, "_006": {"attitudeOfFriend": "NA", "attitude": "NA", "transiency": "neverThoughtAboutIt", "group": "A", "education": "gradeSchoolOrLess", "occupation": "unskilledDomesticPersonalService"}, "_009": {"attitudeOfFriend": "NA", "attitude": "NA", "transiency": "NA", "group": "A", "education": "NA", "occupation": "NA"}, "_008": {"attitudeOfFriend": "NA", "attitude": "NA", "transiency": "untilBetterPlace", "group": "B", "education": "someHighSchool", "occupation": "unskilledDomesticPersonalService"}, "_074": {"attitudeOfFriend": "NA", "attitude": "NA", "transiency": "NA", "group": "B", "education": "someHighSchool", "occupation": "unskilledDomesticPersonalService"}, "_075": {"attitudeOfFriend": "liberalFriend", "attitude": "liberal", "transiency": "NA", "group": "B", "education": "highSchoolGraduate", "occupation": "unskilledDomesticPersonalService"}, "_076": {"attitudeOfFriend": "NA", "attitude": "NA", "transiency": "permanent", "group": "B", "education": "highSchoolGraduate", "occupation": "unskilledDomesticPersonalService"}, "_077": {"attitudeOfFriend": "NA", "attitude": "NA", "transiency": "permanent", "group": "B", "education": "gradeSchoolOrLess", "occupation": "unskilledDomesticPersonalService"}, "_070": {"attitudeOfFriend": "ambivalentFriend", "attitude": "liberal", "transiency": "neverThoughtAboutIt", "group": "A", "education": "NA", "occupation": "NA"}, "_071": {"attitudeOfFriend": "NA", "attitude": "NA", "transiency": "asLongAsEligible", "group": "A", "education": "NA", "occupation": "NA"}, "_072": {"attitudeOfFriend": "ambivalentFriend", "attitude": "liberal", "transiency": "neverThoughtAboutIt", "group": "A", "education": "gradeSchoolOrLess", "occupation": "unskilledDomesticPersonalService"}, "_073": {"attitudeOfFriend": "NA", "attitude": "NA", "transiency": "untilOwnHome", "group": "B", "education": "someHighSchool", "occupation": "semiSkilled"}, "_175": {"attitudeOfFriend": "liberalFriend", "attitude": "liberal", "transiency": "asLongAsEligible", "group": "A", "education": "someHighSchool", "occupation": "whiteColorSkilled"}, "_174": {"attitudeOfFriend": "liberalFriend", "attitude": "liberal", "transiency": "NA", "group": "B", "education": "gradeSchoolOrLess", "occupation": "semiSkilled"}, "_177": {"attitudeOfFriend": "NA", "attitude": "NA", "transiency": "neverThoughtAboutIt", "group": "A", "education": "NA", "occupation": "NA"}, "_176": {"attitudeOfFriend": "NA", "attitude": "NA", "transiency": "untilBetterPlace", "group": "A", "education": "highSchoolGraduate", "occupation": "whiteColorSkilled"}, "_078": {"attitudeOfFriend": "NA", "attitude": "NA", "transiency": "asLongAsEligible", "group": "A", "education": "highSchoolGraduate", "occupation": "whiteColorSkilled"}, "_079": {"attitudeOfFriend": "NA", "attitude": "NA", "transiency": "asLongAsEligible", "group": "A", "education": "someHighSchool", "occupation": "unskilledDomesticPersonalService"}, "_173": {"attitudeOfFriend": "liberalFriend", "attitude": "liberal", "transiency": "NA", "group": "A", "education": "someHighSchool", "occupation": "semiSkilled"}, "_172": {"attitudeOfFriend": "liberalFriend", "attitude": "liberal", "transiency": "asLongAsEligible", "group": "A", "education": "highSchoolGraduate", "occupation": "unskilledDomesticPersonalService"}, "_067": {"attitudeOfFriend": "liberalFriend", "attitude": "liberal", "transiency": "asLongAsEligible", "group": "A", "education": "someHighSchool", "occupation": "unskilledDomesticPersonalService"}, "_066": {"attitudeOfFriend": "liberalFriend", "attitude": "liberal", "transiency": "untilBetterPlace", "group": "A", "education": "NA", "occupation": "NA"}, "_210": {"attitudeOfFriend": "liberalFriend", "attitude": "liberal", "transiency": "asLongAsEligible", "group": "A", "education": "gradeSchoolOrLess", "occupation": "unskilledDomesticPersonalService"}, "_211": {"attitudeOfFriend": "NA", "attitude": "NA", "transiency": "asLongAsEligible", "group": "A", "education": "someHighSchool", "occupation": "unskilledDomesticPersonalService"}, "_212": {"attitudeOfFriend": "NA", "attitude": "NA", "transiency": "asLongAsEligible", "group": "B", "education": "NA", "occupation": "NA"}, "_213": {"attitudeOfFriend": "NA", "attitude": "NA", "transiency": "untilBetterPlace", "group": "A", "education": "NA", "occupation": "NA"}, "_214": {"attitudeOfFriend": "liberalFriend", "attitude": "liberal", "transiency": "neverThoughtAboutIt", "group": "B", "education": "NA", "occupation": "NA"}, "_215": {"attitudeOfFriend": "ambivalentFriend", "attitude": "liberal", "transiency": "untilBetterPlace", "group": "A", "education": "NA", "occupation": "NA"}, "_216": {"attitudeOfFriend": "ambivalentFriend", "attitude": "liberal", "transiency": "untilBetterPlace", "group": "B", "education": "NA", "occupation": "NA"}, "_217": {"attitudeOfFriend": "ambivalentFriend", "attitude": "liberal", "transiency": "asLongAsEligible", "group": "B", "education": "NA", "occupation": "NA"}, "_218": {"attitudeOfFriend": "NA", "attitude": "NA", "transiency": "asLongAsEligible", "group": "A", "education": "highSchoolGraduate", "occupation": "unskilledDomesticPersonalService"}, "_219": {"attitudeOfFriend": "liberalFriend", "attitude": "liberal", "transiency": "permanent", "group": "B", "education": "gradeSchoolOrLess", "occupation": "unskilledDomesticPersonalService"}, "_353": {"attitudeOfFriend": "liberalFriend", "attitude": "liberal", "transiency": "NA", "group": "B", "education": "NA", "occupation": "NA"}, "_352": {"attitudeOfFriend": "NA", "attitude": "NA", "transiency": "neverThoughtAboutIt", "group": "B", "education": "highSchoolGraduate", "occupation": "unskilledDomesticPersonalService"}, "_355": {"attitudeOfFriend": "liberalFriend", "attitude": "liberal", "transiency": "NA", "group": "B", "education": "NA", "occupation": "NA"}, "_354": {"attitudeOfFriend": "NA", "attitude": "NA", "transiency": "untilBetterPlace", "group": "A", "education": "NA", "occupation": "NA"}, "_357": {"attitudeOfFriend": "NA", "attitude": "NA", "transiency": "permanent", "group": "B", "education": "NA", "occupation": "NA"}, "_356": {"attitudeOfFriend": "NA", "attitude": "NA", "transiency": "asLongAsEligible", "group": "A", "education": "NA", "occupation": "NA"}, "_405": {"attitudeOfFriend": "NA", "attitude": "NA", "transiency": "NA", "group": "A", "education": "NA", "occupation": "NA"}, "_404": {"attitudeOfFriend": "liberalFriend", "attitude": "liberal", "transiency": "NA", "group": "A", "education": "NA", "occupation": "NA"}, "_407": {"attitudeOfFriend": "liberalFriend", "attitude": "liberal", "transiency": "permanent", "group": "A", "education": "gradeSchoolOrLess", "occupation": "unskilledDomesticPersonalService"}, "_406": {"attitudeOfFriend": "liberalFriend", "attitude": "liberal", "transiency": "permanent", "group": "B", "education": "someHighSchool", "occupation": "unskilledDomesticPersonalService"}, "_401": {"attitudeOfFriend": "NA", "attitude": "NA", "transiency": "NA", "group": "A", "education": "someHighSchool", "occupation": "unskilledDomesticPersonalService"}, "_106": {"attitudeOfFriend": "NA", "attitude": "NA", "transiency": "asLongAsEligible", "group": "A", "education": "gradeSchoolOrLess", "occupation": "unskilledDomesticPersonalService"}, "_403": {"attitudeOfFriend": "liberalFriend", "attitude": "liberal", "transiency": "asLongAsEligible", "group": "A", "education": "someHighSchool", "occupation": "unskilledDomesticPersonalService"}, "_402": {"attitudeOfFriend": "liberalFriend", "attitude": "liberal", "transiency": "untilBetterPlace", "group": "A", "education": "NA", "occupation": "NA"}, "_107": {"attitudeOfFriend": "NA", "attitude": "NA", "transiency": "asLongAsEligible", "group": "A", "education": "NA", "occupation": "NA"}, "_409": {"attitudeOfFriend": "NA", "attitude": "NA", "transiency": "NA", "group": "A", "education": "NA", "occupation": "NA"}, "_408": {"attitudeOfFriend": "liberalFriend", "attitude": "liberal", "transiency": "untilBetterPlace", "group": "B", "education": "NA", "occupation": "NA"}, "_328": {"attitudeOfFriend": "NA", "attitude": "NA", "transiency": "NA", "group": "B", "education": "someHighSchool", "occupation": "whiteColorSkilled"}, "_329": {"attitudeOfFriend": "liberalFriend", "attitude": "liberal", "transiency": "NA", "group": "A", "education": "someHighSchool", "occupation": "unskilledDomesticPersonalService"}, "_324": {"attitudeOfFriend": "NA", "attitude": "NA", "transiency": "neverThoughtAboutIt", "group": "B", "education": "gradeSchoolOrLess", "occupation": "unskilledDomesticPersonalService"}, "_325": {"attitudeOfFriend": "liberalFriend", "attitude": "liberal", "transiency": "NA", "group": "A", "education": "NA", "occupation": "NA"}, "_326": {"attitudeOfFriend": "liberalFriend", "attitude": "liberal", "transiency": "asLongAsEligible", "group": "A", "education": "gradeSchoolOrLess", "occupation": "unskilledDomesticPersonalService"}, "_327": {"attitudeOfFriend": "liberalFriend", "attitude": "liberal", "transiency": "asLongAsEligible", "group": "A", "education": "highSchoolGraduate", "occupation": "whiteColorSkilled"}, "_320": {"attitudeOfFriend": "NA", "attitude": "NA", "transiency": "asLongAsEligible", "group": "A", "education": "gradeSchoolOrLess", "occupation": "semiSkilled"}, "_321": {"attitudeOfFriend": "NA", "attitude": "NA", "transiency": "NA", "group": "B", "education": "gradeSchoolOrLess", "occupation": "unskilledDomesticPersonalService"}, "_322": {"attitudeOfFriend": "liberalFriend", "attitude": "liberal", "transiency": "asLongAsEligible", "group": "A", "education": "NA", "occupation": "NA"}, "_323": {"attitudeOfFriend": "liberalFriend", "attitude": "liberal", "transiency": "untilBetterPlace", "group": "A", "education": "gradeSchoolOrLess", "occupation": "unskilledDomesticPersonalService"}, "_289": {"attitudeOfFriend": "NA", "attitude": "NA", "transiency": "NA", "group": "A", "education": "someHighSchool", "occupation": "unskilledDomesticPersonalService"}, "_288": {"attitudeOfFriend": "NA", "attitude": "NA", "transiency": "asLongAsEligible", "group": "B", "education": "gradeSchoolOrLess", "occupation": "unskilledDomesticPersonalService"}, "_283": {"attitudeOfFriend": "NA", "attitude": "NA", "transiency": "NA", "group": "A", "education": "NA", "occupation": "NA"}, "_282": {"attitudeOfFriend": "liberalFriend", "attitude": "liberal", "transiency": "asLongAsEligible", "group": "A", "education": "NA", "occupation": "NA"}, "_281": {"attitudeOfFriend": "NA", "attitude": "NA", "transiency": "untilOwnHome", "group": "B", "education": "highSchoolGraduate", "occupation": "unskilledDomesticPersonalService"}, "_280": {"attitudeOfFriend": "liberalFriend", "attitude": "liberal", "transiency": "asLongAsEligible", "group": "A", "education": "NA", "occupation": "NA"}, "_287": {"attitudeOfFriend": "NA", "attitude": "NA", "transiency": "untilBetterPlace", "group": "A", "education": "someHighSchool", "occupation": "semiSkilled"}, "_286": {"attitudeOfFriend": "NA", "attitude": "NA", "transiency": "asLongAsEligible", "group": "A", "education": "someHighSchool", "occupation": "semiSkilled"}, "_285": {"attitudeOfFriend": "NA", "attitude": "NA", "transiency": "asLongAsEligible", "group": "B", "education": "NA", "occupation": "NA"}, "_284": {"attitudeOfFriend": "NA", "attitude": "NA", "transiency": "permanent", "group": "B", "education": "gradeSchoolOrLess", "occupation": "semiSkilled"}, "_358": {"attitudeOfFriend": "NA", "attitude": "NA", "transiency": "permanent", "group": "B", "education": "someHighSchool", "occupation": "unskilledDomesticPersonalService"}, "_131": {"attitudeOfFriend": "liberalFriend", "attitude": "liberal", "transiency": "untilBetterPlace", "group": "B", "education": "someHighSchool", "occupation": "unskilledDomesticPersonalService"}, "_130": {"attitudeOfFriend": "NA", "attitude": "NA", "transiency": "untilOwnHome", "group": "B", "education": "gradeSchoolOrLess", "occupation": "unskilledDomesticPersonalService"}, "_133": {"attitudeOfFriend": "liberalFriend", "attitude": "liberal", "transiency": "NA", "group": "A", "education": "gradeSchoolOrLess", "occupation": "unskilledDomesticPersonalService"}, "_132": {"attitudeOfFriend": "liberalFriend", "attitude": "liberal", "transiency": "NA", "group": "B", "education": "highSchoolGraduate", "occupation": "unskilledDomesticPersonalService"}, "_135": {"attitudeOfFriend": "NA", "attitude": "NA", "transiency": "asLongAsEligible", "group": "B", "education": "someHighSchool", "occupation": "unskilledDomesticPersonalService"}, "_134": {"attitudeOfFriend": "NA", "attitude": "NA", "transiency": "permanent", "group": "A", "education": "highSchoolGraduate", "occupation": "whiteColorSkilled"}, "_137": {"attitudeOfFriend": "NA", "attitude": "NA", "transiency": "asLongAsEligible", "group": "A", "education": "gradeSchoolOrLess", "occupation": "unskilledDomesticPersonalService"}, "_136": {"attitudeOfFriend": "NA", "attitude": "NA", "transiency": "NA", "group": "B", "education": "gradeSchoolOrLess", "occupation": "unskilledDomesticPersonalService"}, "_139": {"attitudeOfFriend": "liberalFriend", "attitude": "liberal", "transiency": "asLongAsEligible", "group": "A", "education": "NA", "occupation": "NA"}, "_138": {"attitudeOfFriend": "NA", "attitude": "NA", "transiency": "asLongAsEligible", "group": "B", "education": "gradeSchoolOrLess", "occupation": "semiSkilled"}, "_038": {"attitudeOfFriend": "NA", "attitude": "NA", "transiency": "NA", "group": "B", "education": "NA", "occupation": "NA"}, "_039": {"attitudeOfFriend": "NA", "attitude": "NA", "transiency": "NA", "group": "A", "education": "gradeSchoolOrLess", "occupation": "unskilledDomesticPersonalService"}, "_030": {"attitudeOfFriend": "NA", "attitude": "NA", "transiency": "untilBetterPlace", "group": "B", "education": "someHighSchool", "occupation": "unskilledDomesticPersonalService"}, "_031": {"attitudeOfFriend": "liberalFriend", "attitude": "liberal", "transiency": "permanent", "group": "A", "education": "gradeSchoolOrLess", "occupation": "unskilledDomesticPersonalService"}, "_032": {"attitudeOfFriend": "liberalFriend", "attitude": "ambivalent", "transiency": "asLongAsEligible", "group": "A", "education": "gradeSchoolOrLess", "occupation": "whiteColorSkilled"}, "_033": {"attitudeOfFriend": "liberalFriend", "attitude": "liberal", "transiency": "permanent", "group": "B", "education": "gradeSchoolOrLess", "occupation": "whiteColorSkilled"}, "_034": {"attitudeOfFriend": "liberalFriend", "attitude": "liberal", "transiency": "untilBetterPlace", "group": "A", "education": "NA", "occupation": "NA"}, "_035": {"attitudeOfFriend": "NA", "attitude": "NA", "transiency": "asLongAsEligible", "group": "B", "education": "someHighSchool", "occupation": "unskilledDomesticPersonalService"}, "_036": {"attitudeOfFriend": "liberalFriend", "attitude": "liberal", "transiency": "permanent", "group": "B", "education": "someHighSchool", "occupation": "unskilledDomesticPersonalService"}, "_037": {"attitudeOfFriend": "liberalFriend", "attitude": "liberal", "transiency": "NA", "group": "A", "education": "NA", "occupation": "NA"}, "_144": {"attitudeOfFriend": "liberalFriend", "attitude": "liberal", "transiency": "NA", "group": "A", "education": "NA", "occupation": "NA"}, "_145": {"attitudeOfFriend": "liberalFriend", "attitude": "liberal", "transiency": "asLongAsEligible", "group": "B", "education": "NA", "occupation": "NA"}, "_146": {"attitudeOfFriend": "NA", "attitude": "NA", "transiency": "permanent", "group": "B", "education": "someHighSchool", "occupation": "whiteColorSkilled"}, "_147": {"attitudeOfFriend": "NA", "attitude": "NA", "transiency": "neverThoughtAboutIt", "group": "A", "education": "gradeSchoolOrLess", "occupation": "semiSkilled"}, "_140": {"attitudeOfFriend": "ambivalentFriend", "attitude": "ambivalent", "transiency": "NA", "group": "B", "education": "someHighSchool", "occupation": "unskilledDomesticPersonalService"}, "_141": {"attitudeOfFriend": "liberalFriend", "attitude": "liberal", "transiency": "permanent", "group": "A", "education": "someHighSchool", "occupation": "unskilledDomesticPersonalService"}, "_142": {"attitudeOfFriend": "liberalFriend", "attitude": "liberal", "transiency": "permanent", "group": "B", "education": "NA", "occupation": "NA"}, "_143": {"attitudeOfFriend": "NA", "attitude": "NA", "transiency": "NA", "group": "B", "education": "highSchoolGraduate", "occupation": "unskilledDomesticPersonalService"}, "_148": {"attitudeOfFriend": "liberalFriend", "attitude": "liberal", "transiency": "NA", "group": "A", "education": "NA", "occupation": "NA"}, "_149": {"attitudeOfFriend": "NA", "attitude": "NA", "transiency": "NA", "group": "B", "education": "NA", "occupation": "NA"}, "_449": {"attitudeOfFriend": "NA", "attitude": "NA", "transiency": "NA", "group": "B", "education": "NA", "occupation": "NA"}, "_448": {"attitudeOfFriend": "NA", "attitude": "NA", "transiency": "NA", "group": "B", "education": "NA", "occupation": "NA"}, "_441": {"attitudeOfFriend": "liberalFriend", "attitude": "liberal", "transiency": "NA", "group": "B", "education": "someHighSchool", "occupation": "unskilledDomesticPersonalService"}, "_440": {"attitudeOfFriend": "liberalFriend", "attitude": "liberal", "transiency": "asLongAsEligible", "group": "B", "education": "someHighSchool", "occupation": "unskilledDomesticPersonalService"}, "_443": {"attitudeOfFriend": "liberalFriend", "attitude": "ambivalent", "transiency": "asLongAsEligible", "group": "B", "education": "gradeSchoolOrLess", "occupation": "unskilledDomesticPersonalService"}, "_442": {"attitudeOfFriend": "liberalFriend", "attitude": "liberal", "transiency": "NA", "group": "A", "education": "NA", "occupation": "NA"}, "_445": {"attitudeOfFriend": "liberalFriend", "attitude": "liberal", "transiency": "permanent", "group": "B", "education": "gradeSchoolOrLess", "occupation": "unskilledDomesticPersonalService"}, "_444": {"attitudeOfFriend": "NA", "attitude": "NA", "transiency": "untilOwnHome", "group": "B", "education": "someHighSchool", "occupation": "unskilledDomesticPersonalService"}, "_447": {"attitudeOfFriend": "ambivalentFriend", "attitude": "ambivalent", "transiency": "asLongAsEligible", "group": "A", "education": "gradeSchoolOrLess", "occupation": "unskilledDomesticPersonalService"}, "_446": {"attitudeOfFriend": "liberalFriend", "attitude": "liberal", "transiency": "asLongAsEligible", "group": "A", "education": "gradeSchoolOrLess", "occupation": "whiteColorSkilled"}, "_089": {"attitudeOfFriend": "liberalFriend", "attitude": "ambivalent", "transiency": "neverThoughtAboutIt", "group": "B", "education": "someHighSchool", "occupation": "semiSkilled"}, "_088": {"attitudeOfFriend": "NA", "attitude": "NA", "transiency": "asLongAsEligible", "group": "A", "education": "someHighSchool", "occupation": "unskilledDomesticPersonalService"}, "_362": {"attitudeOfFriend": "liberalFriend", "attitude": "liberal", "transiency": "NA", "group": "B", "education": "someHighSchool", "occupation": "unskilledDomesticPersonalService"}, "_363": {"attitudeOfFriend": "NA", "attitude": "NA", "transiency": "untilBetterPlace", "group": "B", "education": "gradeSchoolOrLess", "occupation": "unskilledDomesticPersonalService"}, "_364": {"attitudeOfFriend": "liberalFriend", "attitude": "liberal", "transiency": "untilOwnHome", "group": "B", "education": "gradeSchoolOrLess", "occupation": "unskilledDomesticPersonalService"}, "_365": {"attitudeOfFriend": "NA", "attitude": "NA", "transiency": "untilOwnHome", "group": "A", "education": "NA", "occupation": "NA"}, "_366": {"attitudeOfFriend": "NA", "attitude": "NA", "transiency": "permanent", "group": "A", "education": "gradeSchoolOrLess", "occupation": "semiSkilled"}, "_367": {"attitudeOfFriend": "NA", "attitude": "NA", "transiency": "neverThoughtAboutIt", "group": "A", "education": "gradeSchoolOrLess", "occupation": "unskilledDomesticPersonalService"}, "_081": {"attitudeOfFriend": "NA", "attitude": "NA", "transiency": "NA", "group": "B", "education": "highSchoolGraduate", "occupation": "unskilledDomesticPersonalService"}, "_080": {"attitudeOfFriend": "liberalFriend", "attitude": "liberal", "transiency": "asLongAsEligible", "group": "A", "education": "gradeSchoolOrLess", "occupation": "unskilledDomesticPersonalService"}, "_083": {"attitudeOfFriend": "NA", "attitude": "NA", "transiency": "NA", "group": "B", "education": "gradeSchoolOrLess", "occupation": "unskilledDomesticPersonalService"}, "_082": {"attitudeOfFriend": "liberalFriend", "attitude": "liberal", "transiency": "NA", "group": "B", "education": "gradeSchoolOrLess", "occupation": "unskilledDomesticPersonalService"}, "_085": {"attitudeOfFriend": "NA", "attitude": "NA", "transiency": "asLongAsEligible", "group": "A", "education": "someHighSchool", "occupation": "whiteColorSkilled"}, "_084": {"attitudeOfFriend": "liberalFriend", "attitude": "liberal", "transiency": "asLongAsEligible", "group": "A", "education": "someHighSchool", "occupation": "whiteColorSkilled"}, "_087": {"attitudeOfFriend": "NA", "attitude": "NA", "transiency": "NA", "group": "B", "education": "someHighSchool", "occupation": "whiteColorSkilled"}, "_086": {"attitudeOfFriend": "NA", "attitude": "NA", "transiency": "asLongAsEligible", "group": "B", "education": "someHighSchool", "occupation": "unskilledDomesticPersonalService"}, "_249": {"attitudeOfFriend": "liberalFriend", "attitude": "liberal", "transiency": "asLongAsEligible", "group": "A", "education": "someHighSchool", "occupation": "unskilledDomesticPersonalService"}, "_248": {"attitudeOfFriend": "liberalFriend", "attitude": "liberal", "transiency": "asLongAsEligible", "group": "A", "education": "highSchoolGraduate", "occupation": "whiteColorSkilled"}, "_247": {"attitudeOfFriend": "liberalFriend", "attitude": "liberal", "transiency": "NA", "group": "A", "education": "gradeSchoolOrLess", "occupation": "unskilledDomesticPersonalService"}, "_246": {"attitudeOfFriend": "NA", "attitude": "NA", "transiency": "untilBetterPlace", "group": "A", "education": "NA", "occupation": "NA"}, "_245": {"attitudeOfFriend": "NA", "attitude": "NA", "transiency": "NA", "group": "A", "education": "gradeSchoolOrLess", "occupation": "semiSkilled"}, "_244": {"attitudeOfFriend": "liberalFriend", "attitude": "liberal", "transiency": "permanent", "group": "B", "education": "NA", "occupation": "NA"}, "_243": {"attitudeOfFriend": "liberalFriend", "attitude": "ambivalent", "transiency": "asLongAsEligible", "group": "B", "education": "NA", "occupation": "NA"}, "_242": {"attitudeOfFriend": "NA", "attitude": "NA", "transiency": "untilOwnHome", "group": "A", "education": "NA", "occupation": "NA"}, "_241": {"attitudeOfFriend": "NA", "attitude": "NA", "transiency": "NA", "group": "B", "education": "NA", "occupation": "NA"}, "_240": {"attitudeOfFriend": "NA", "attitude": "NA", "transiency": "NA", "group": "B", "education": "highSchoolGraduate", "occupation": "semiSkilled"}, "_438": {"attitudeOfFriend": "ambivalentFriend", "attitude": "liberal", "transiency": "NA", "group": "A", "education": "gradeSchoolOrLess", "occupation": "whiteColorSkilled"}, "_439": {"attitudeOfFriend": "NA", "attitude": "NA", "transiency": "untilBetterPlace", "group": "B", "education": "someHighSchool", "occupation": "unskilledDomesticPersonalService"}, "_434": {"attitudeOfFriend": "NA", "attitude": "NA", "transiency": "untilOwnHome", "group": "A", "education": "gradeSchoolOrLess", "occupation": "unskilledDomesticPersonalService"}, "_435": {"attitudeOfFriend": "liberalFriend", "attitude": "liberal", "transiency": "permanent", "group": "A", "education": "NA", "occupation": "NA"}, "_436": {"attitudeOfFriend": "NA", "attitude": "NA", "transiency": "asLongAsEligible", "group": "B", "education": "NA", "occupation": "NA"}, "_437": {"attitudeOfFriend": "liberalFriend", "attitude": "liberal", "transiency": "asLongAsEligible", "group": "A", "education": "highSchoolGraduate", "occupation": "semiSkilled"}, "_430": {"attitudeOfFriend": "liberalFriend", "attitude": "liberal", "transiency": "neverThoughtAboutIt", "group": "B", "education": "someHighSchool", "occupation": "unskilledDomesticPersonalService"}, "_431": {"attitudeOfFriend": "liberalFriend", "attitude": "liberal", "transiency": "neverThoughtAboutIt", "group": "A", "education": "gradeSchoolOrLess", "occupation": "semiSkilled"}, "_432": {"attitudeOfFriend": "ambivalentFriend", "attitude": "ambivalent", "transiency": "permanent", "group": "A", "education": "gradeSchoolOrLess", "occupation": "unskilledDomesticPersonalService"}, "_433": {"attitudeOfFriend": "NA", "attitude": "NA", "transiency": "neverThoughtAboutIt", "group": "A", "education": "NA", "occupation": "NA"}, "_108": {"attitudeOfFriend": "liberalFriend", "attitude": "liberal", "transiency": "NA", "group": "B", "education": "NA", "occupation": "NA"}, "_109": {"attitudeOfFriend": "ambivalentFriend", "attitude": "liberal", "transiency": "NA", "group": "A", "education": "someHighSchool", "occupation": "unskilledDomesticPersonalService"}, "_065": {"attitudeOfFriend": "liberalFriend", "attitude": "liberal", "transiency": "untilOwnHome", "group": "A", "education": "someHighSchool", "occupation": "unskilledDomesticPersonalService"}, "_064": {"attitudeOfFriend": "liberalFriend", "attitude": "liberal", "transiency": "permanent", "group": "A", "education": "NA", "occupation": "NA"}, "_063": {"attitudeOfFriend": "liberalFriend", "attitude": "liberal", "transiency": "neverThoughtAboutIt", "group": "A", "education": "gradeSchoolOrLess", "occupation": "unskilledDomesticPersonalService"}, "_062": {"attitudeOfFriend": "liberalFriend", "attitude": "liberal", "transiency": "NA", "group": "B", "education": "someHighSchool", "occupation": "unskilledDomesticPersonalService"}, "_061": {"attitudeOfFriend": "NA", "attitude": "NA", "transiency": "permanent", "group": "B", "education": "NA", "occupation": "NA"}, "_060": {"attitudeOfFriend": "NA", "attitude": "NA", "transiency": "asLongAsEligible", "group": "B", "education": "highSchoolGraduate", "occupation": "semiSkilled"}, "_100": {"attitudeOfFriend": "liberalFriend", "attitude": "liberal", "transiency": "neverThoughtAboutIt", "group": "A", "education": "gradeSchoolOrLess", "occupation": "unskilledDomesticPersonalService"}, "_101": {"attitudeOfFriend": "liberalFriend", "attitude": "liberal", "transiency": "untilBetterPlace", "group": "A", "education": "gradeSchoolOrLess", "occupation": "unskilledDomesticPersonalService"}, "_102": {"attitudeOfFriend": "liberalFriend", "attitude": "liberal", "transiency": "asLongAsEligible", "group": "B", "education": "gradeSchoolOrLess", "occupation": "semiSkilled"}, "_103": {"attitudeOfFriend": "liberalFriend", "attitude": "liberal", "transiency": "neverThoughtAboutIt", "group": "A", "education": "NA", "occupation": "NA"}, "_104": {"attitudeOfFriend": "ambivalentFriend", "attitude": "liberal", "transiency": "untilBetterPlace", "group": "A", "education": "someHighSchool", "occupation": "unskilledDomesticPersonalService"}, "_105": {"attitudeOfFriend": "liberalFriend", "attitude": "liberal", "transiency": "permanent", "group": "B", "education": "NA", "occupation": "NA"}, "_069": {"attitudeOfFriend": "NA", "attitude": "NA", "transiency": "asLongAsEligible", "group": "A", "education": "NA", "occupation": "NA"}, "_068": {"attitudeOfFriend": "liberalFriend", "attitude": "liberal", "transiency": "asLongAsEligible", "group": "A", "education": "highSchoolGraduate", "occupation": "whiteColorSkilled"}, "_203": {"attitudeOfFriend": "NA", "attitude": "NA", "transiency": "asLongAsEligible", "group": "B", "education": "highSchoolGraduate", "occupation": "whiteColorSkilled"}, "_202": {"attitudeOfFriend": "liberalFriend", "attitude": "liberal", "transiency": "permanent", "group": "B", "education": "NA", "occupation": "NA"}, "_201": {"attitudeOfFriend": "NA", "attitude": "NA", "transiency": "asLongAsEligible", "group": "A", "education": "someHighSchool", "occupation": "whiteColorSkilled"}, "_200": {"attitudeOfFriend": "liberalFriend", "attitude": "liberal", "transiency": "asLongAsEligible", "group": "A", "education": "gradeSchoolOrLess", "occupation": "unskilledDomesticPersonalService"}, "_207": {"attitudeOfFriend": "NA", "attitude": "NA", "transiency": "permanent", "group": "B", "education": "gradeSchoolOrLess", "occupation": "unskilledDomesticPersonalService"}, "_206": {"attitudeOfFriend": "liberalFriend", "attitude": "liberal", "transiency": "neverThoughtAboutIt", "group": "A", "education": "gradeSchoolOrLess", "occupation": "whiteColorSkilled"}, "_205": {"attitudeOfFriend": "NA", "attitude": "NA", "transiency": "permanent", "group": "B", "education": "someHighSchool", "occupation": "unskilledDomesticPersonalService"}, "_204": {"attitudeOfFriend": "NA", "attitude": "NA", "transiency": "asLongAsEligible", "group": "B", "education": "NA", "occupation": "NA"}, "_209": {"attitudeOfFriend": "NA", "attitude": "NA", "transiency": "neverThoughtAboutIt", "group": "B", "education": "gradeSchoolOrLess", "occupation": "unskilledDomesticPersonalService"}, "_208": {"attitudeOfFriend": "NA", "attitude": "NA", "transiency": "asLongAsEligible", "group": "A", "education": "highSchoolGraduate", "occupation": "unskilledDomesticPersonalService"}, "_470": {"attitudeOfFriend": "NA", "attitude": "NA", "transiency": "asLongAsEligible", "group": "B", "education": "highSchoolGraduate", "occupation": "semiSkilled"}, "_471": {"attitudeOfFriend": "liberalFriend", "attitude": "liberal", "transiency": "NA", "group": "A", "education": "someHighSchool", "occupation": "unskilledDomesticPersonalService"}, "_472": {"attitudeOfFriend": "liberalFriend", "attitude": "ambivalent", "transiency": "permanent", "group": "B", "education": "someHighSchool", "occupation": "unskilledDomesticPersonalService"}, "_473": {"attitudeOfFriend": "NA", "attitude": "NA", "transiency": "NA", "group": "A", "education": "gradeSchoolOrLess", "occupation": "unskilledDomesticPersonalService"}, "_474": {"attitudeOfFriend": "NA", "attitude": "NA", "transiency": "permanent", "group": "B", "education": "highSchoolGraduate", "occupation": "unskilledDomesticPersonalService"}, "_475": {"attitudeOfFriend": "liberalFriend", "attitude": "liberal", "transiency": "asLongAsEligible", "group": "B", "education": "gradeSchoolOrLess", "occupation": "semiSkilled"}, "_476": {"attitudeOfFriend": "NA", "attitude": "NA", "transiency": "untilBetterPlace", "group": "A", "education": "highSchoolGraduate", "occupation": "unskilledDomesticPersonalService"}, "_477": {"attitudeOfFriend": "liberalFriend", "attitude": "liberal", "transiency": "NA", "group": "A", "education": "highSchoolGraduate", "occupation": "semiSkilled"}, "_478": {"attitudeOfFriend": "NA", "attitude": "NA", "transiency": "untilBetterPlace", "group": "B", "education": "highSchoolGraduate", "occupation": "whiteColorSkilled"}, "_179": {"attitudeOfFriend": "NA", "attitude": "NA", "transiency": "NA", "group": "A", "education": "NA", "occupation": "NA"}, "_178": {"attitudeOfFriend": "liberalFriend", "attitude": "liberal", "transiency": "neverThoughtAboutIt", "group": "A", "education": "highSchoolGraduate", "occupation": "semiSkilled"}, "_171": {"attitudeOfFriend": "NA", "attitude": "NA", "transiency": "untilBetterPlace", "group": "B", "education": "NA", "occupation": "NA"}, "_170": {"attitudeOfFriend": "liberalFriend", "attitude": "liberal", "transiency": "NA", "group": "B", "education": "someHighSchool", "occupation": "unskilledDomesticPersonalService"}, "_339": {"attitudeOfFriend": "NA", "attitude": "NA", "transiency": "NA", "group": "A", "education": "NA", "occupation": "NA"}, "_338": {"attitudeOfFriend": "liberalFriend", "attitude": "liberal", "transiency": "NA", "group": "B", "education": "gradeSchoolOrLess", "occupation": "semiSkilled"}, "_337": {"attitudeOfFriend": "liberalFriend", "attitude": "liberal", "transiency": "permanent", "group": "B", "education": "gradeSchoolOrLess", "occupation": "unskilledDomesticPersonalService"}, "_336": {"attitudeOfFriend": "NA", "attitude": "NA", "transiency": "NA", "group": "B", "education": "NA", "occupation": "NA"}, "_335": {"attitudeOfFriend": "NA", "attitude": "NA", "transiency": "NA", "group": "A", "education": "NA", "occupation": "NA"}, "_334": {"attitudeOfFriend": "NA", "attitude": "NA", "transiency": "asLongAsEligible", "group": "A", "education": "gradeSchoolOrLess", "occupation": "unskilledDomesticPersonalService"}, "_333": {"attitudeOfFriend": "NA", "attitude": "NA", "transiency": "neverThoughtAboutIt", "group": "A", "education": "NA", "occupation": "NA"}, "_332": {"attitudeOfFriend": "liberalFriend", "attitude": "liberal", "transiency": "untilBetterPlace", "group": "B", "education": "NA", "occupation": "NA"}, "_331": {"attitudeOfFriend": "ambivalentFriend", "attitude": "liberal", "transiency": "untilBetterPlace", "group": "A", "education": "someHighSchool", "occupation": "semiSkilled"}, "_330": {"attitudeOfFriend": "liberalFriend", "attitude": "liberal", "transiency": "neverThoughtAboutIt", "group": "A", "education": "gradeSchoolOrLess", "occupation": "unskilledDomesticPersonalService"}, "_500": {"attitudeOfFriend": "NA", "attitude": "NA", "transiency": "asLongAsEligible", "group": "B", "education": "someHighSchool", "occupation": "whiteColorSkilled"}, "_501": {"attitudeOfFriend": "NA", "attitude": "NA", "transiency": "untilBetterPlace", "group": "B", "education": "gradeSchoolOrLess", "occupation": "unskilledDomesticPersonalService"}, "_382": {"attitudeOfFriend": "NA", "attitude": "NA", "transiency": "neverThoughtAboutIt", "group": "B", "education": "highSchoolGraduate", "occupation": "unskilledDomesticPersonalService"}, "_383": {"attitudeOfFriend": "ambivalentFriend", "attitude": "liberal", "transiency": "neverThoughtAboutIt", "group": "B", "education": "gradeSchoolOrLess", "occupation": "unskilledDomesticPersonalService"}, "_029": {"attitudeOfFriend": "liberalFriend", "attitude": "ambivalent", "transiency": "neverThoughtAboutIt", "group": "A", "education": "someHighSchool", "occupation": "unskilledDomesticPersonalService"}, "_028": {"attitudeOfFriend": "liberalFriend", "attitude": "liberal", "transiency": "asLongAsEligible", "group": "A", "education": "NA", "occupation": "NA"}, "_386": {"attitudeOfFriend": "liberalFriend", "attitude": "ambivalent", "transiency": "NA", "group": "A", "education": "NA", "occupation": "NA"}, "_387": {"attitudeOfFriend": "NA", "attitude": "NA", "transiency": "neverThoughtAboutIt", "group": "B", "education": "NA", "occupation": "NA"}, "_384": {"attitudeOfFriend": "NA", "attitude": "NA", "transiency": "asLongAsEligible", "group": "A", "education": "gradeSchoolOrLess", "occupation": "unskilledDomesticPersonalService"}, "_385": {"attitudeOfFriend": "liberalFriend", "attitude": "liberal", "transiency": "asLongAsEligible", "group": "B", "education": "someHighSchool", "occupation": "unskilledDomesticPersonalService"}, "_023": {"attitudeOfFriend": "NA", "attitude": "NA", "transiency": "asLongAsEligible", "group": "B", "education": "someHighSchool", "occupation": "semiSkilled"}, "_022": {"attitudeOfFriend": "liberalFriend", "attitude": "liberal", "transiency": "neverThoughtAboutIt", "group": "A", "education": "NA", "occupation": "NA"}, "_021": {"attitudeOfFriend": "NA", "attitude": "NA", "transiency": "NA", "group": "B", "education": "NA", "occupation": "NA"}, "_020": {"attitudeOfFriend": "liberalFriend", "attitude": "liberal", "transiency": "untilOwnHome", "group": "B", "education": "NA", "occupation": "NA"}, "_027": {"attitudeOfFriend": "NA", "attitude": "NA", "transiency": "NA", "group": "A", "education": "gradeSchoolOrLess", "occupation": "unskilledDomesticPersonalService"}, "_026": {"attitudeOfFriend": "NA", "attitude": "NA", "transiency": "NA", "group": "B", "education": "gradeSchoolOrLess", "occupation": "unskilledDomesticPersonalService"}, "_025": {"attitudeOfFriend": "liberalFriend", "attitude": "liberal", "transiency": "asLongAsEligible", "group": "B", "education": "NA", "occupation": "NA"}, "_024": {"attitudeOfFriend": "NA", "attitude": "NA", "transiency": "neverThoughtAboutIt", "group": "B", "education": "gradeSchoolOrLess", "occupation": "unskilledDomesticPersonalService"}, "_093": {"attitudeOfFriend": "NA", "attitude": "NA", "transiency": "asLongAsEligible", "group": "B", "education": "NA", "occupation": "NA"}, "_157": {"attitudeOfFriend": "NA", "attitude": "NA", "transiency": "untilBetterPlace", "group": "B", "education": "gradeSchoolOrLess", "occupation": "unskilledDomesticPersonalService"}, "_156": {"attitudeOfFriend": "liberalFriend", "attitude": "liberal", "transiency": "untilBetterPlace", "group": "B", "education": "NA", "occupation": "NA"}, "_155": {"attitudeOfFriend": "NA", "attitude": "NA", "transiency": "permanent", "group": "A", "education": "gradeSchoolOrLess", "occupation": "unskilledDomesticPersonalService"}, "_154": {"attitudeOfFriend": "liberalFriend", "attitude": "liberal", "transiency": "permanent", "group": "A", "education": "gradeSchoolOrLess", "occupation": "unskilledDomesticPersonalService"}, "_153": {"attitudeOfFriend": "NA", "attitude": "NA", "transiency": "NA", "group": "B", "education": "NA", "occupation": "NA"}, "_152": {"attitudeOfFriend": "liberalFriend", "attitude": "liberal", "transiency": "NA", "group": "A", "education": "someHighSchool", "occupation": "unskilledDomesticPersonalService"}, "_151": {"attitudeOfFriend": "liberalFriend", "attitude": "ambivalent", "transiency": "neverThoughtAboutIt", "group": "A", "education": "gradeSchoolOrLess", "occupation": "unskilledDomesticPersonalService"}, "_150": {"attitudeOfFriend": "NA", "attitude": "NA", "transiency": "neverThoughtAboutIt", "group": "A", "education": "someHighSchool", "occupation": "unskilledDomesticPersonalService"}, "_159": {"attitudeOfFriend": "NA", "attitude": "NA", "transiency": "NA", "group": "A", "education": "someHighSchool", "occupation": "unskilledDomesticPersonalService"}, "_158": {"attitudeOfFriend": "ambivalentFriend", "attitude": "liberal", "transiency": "untilBetterPlace", "group": "A", "education": "gradeSchoolOrLess", "occupation": "unskilledDomesticPersonalService"}, "_479": {"attitudeOfFriend": "liberalFriend", "attitude": "liberal", "transiency": "neverThoughtAboutIt", "group": "B", "education": "gradeSchoolOrLess", "occupation": "whiteColorSkilled"}, "_319": {"attitudeOfFriend": "ambivalentFriend", "attitude": "liberal", "transiency": "NA", "group": "B", "education": "NA", "occupation": "NA"}, "_373": {"attitudeOfFriend": "NA", "attitude": "NA", "transiency": "untilBetterPlace", "group": "B", "education": "gradeSchoolOrLess", "occupation": "unskilledDomesticPersonalService"}, "_372": {"attitudeOfFriend": "NA", "attitude": "NA", "transiency": "asLongAsEligible", "group": "B", "education": "NA", "occupation": "NA"}, "_371": {"attitudeOfFriend": "NA", "attitude": "NA", "transiency": "NA", "group": "B", "education": "NA", "occupation": "NA"}, "_370": {"attitudeOfFriend": "ambivalentFriend", "attitude": "liberal", "transiency": "untilBetterPlace", "group": "B", "education": "NA", "occupation": "NA"}, "_377": {"attitudeOfFriend": "NA", "attitude": "NA", "transiency": "NA", "group": "A", "education": "highSchoolGraduate", "occupation": "semiSkilled"}, "_376": {"attitudeOfFriend": "NA", "attitude": "NA", "transiency": "asLongAsEligible", "group": "A", "education": "highSchoolGraduate", "occupation": "unskilledDomesticPersonalService"}, "_375": {"attitudeOfFriend": "liberalFriend", "attitude": "liberal", "transiency": "NA", "group": "B", "education": "NA", "occupation": "NA"}, "_374": {"attitudeOfFriend": "liberalFriend", "attitude": "liberal", "transiency": "NA", "group": "B", "education": "NA", "occupation": "NA"}, "_379": {"attitudeOfFriend": "ambivalentFriend", "attitude": "liberal", "transiency": "asLongAsEligible", "group": "A", "education": "gradeSchoolOrLess", "occupation": "unskilledDomesticPersonalService"}, "_378": {"attitudeOfFriend": "ambivalentFriend", "attitude": "liberal", "transiency": "NA", "group": "A", "education": "NA", "occupation": "NA"}, "_278": {"attitudeOfFriend": "liberalFriend", "attitude": "liberal", "transiency": "neverThoughtAboutIt", "group": "B", "education": "NA", "occupation": "NA"}, "_279": {"attitudeOfFriend": "NA", "attitude": "NA", "transiency": "asLongAsEligible", "group": "A", "education": "NA", "occupation": "NA"}, "_272": {"attitudeOfFriend": "liberalFriend", "attitude": "liberal", "transiency": "untilBetterPlace", "group": "A", "education": "gradeSchoolOrLess", "occupation": "semiSkilled"}, "_273": {"attitudeOfFriend": "liberalFriend", "attitude": "liberal", "transiency": "asLongAsEligible", "group": "B", "education": "NA", "occupation": "NA"}, "_270": {"attitudeOfFriend": "NA", "attitude": "NA", "transiency": "untilBetterPlace", "group": "B", "education": "someHighSchool", "occupation": "whiteColorSkilled"}, "_271": {"attitudeOfFriend": "liberalFriend", "attitude": "liberal", "transiency": "untilBetterPlace", "group": "B", "education": "gradeSchoolOrLess", "occupation": "unskilledDomesticPersonalService"}, "_276": {"attitudeOfFriend": "liberalFriend", "attitude": "liberal", "transiency": "untilBetterPlace", "group": "B", "education": "NA", "occupation": "NA"}, "_277": {"attitudeOfFriend": "NA", "attitude": "NA", "transiency": "asLongAsEligible", "group": "A", "education": "gradeSchoolOrLess", "occupation": "unskilledDomesticPersonalService"}, "_274": {"attitudeOfFriend": "liberalFriend", "attitude": "liberal", "transiency": "NA", "group": "B", "education": "NA", "occupation": "NA"}, "_275": {"attitudeOfFriend": "NA", "attitude": "NA", "transiency": "untilOwnHome", "group": "B", "education": "NA", "occupation": "NA"}, "_429": {"attitudeOfFriend": "NA", "attitude": "NA", "transiency": "asLongAsEligible", "group": "A", "education": "someHighSchool", "occupation": "unskilledDomesticPersonalService"}, "_428": {"attitudeOfFriend": "NA", "attitude": "NA", "transiency": "asLongAsEligible", "group": "A", "education": "NA", "occupation": "NA"}, "_427": {"attitudeOfFriend": "NA", "attitude": "NA", "transiency": "untilOwnHome", "group": "A", "education": "NA", "occupation": "NA"}, "_426": {"attitudeOfFriend": "liberalFriend", "attitude": "liberal", "transiency": "untilOwnHome", "group": "A", "education": "gradeSchoolOrLess", "occupation": "unskilledDomesticPersonalService"}, "_425": {"attitudeOfFriend": "NA", "attitude": "NA", "transiency": "asLongAsEligible", "group": "B", "education": "gradeSchoolOrLess", "occupation": "whiteColorSkilled"}, "_424": {"attitudeOfFriend": "NA", "attitude": "NA", "transiency": "NA", "group": "B", "education": "gradeSchoolOrLess", "occupation": "whiteColorSkilled"}, "_423": {"attitudeOfFriend": "ambivalentFriend", "attitude": "liberal", "transiency": "untilBetterPlace", "group": "A", "education": "NA", "occupation": "NA"}, "_422": {"attitudeOfFriend": "NA", "attitude": "NA", "transiency": "untilBetterPlace", "group": "B", "education": "highSchoolGraduate", "occupation": "unskilledDomesticPersonalService"}, "_421": {"attitudeOfFriend": "liberalFriend", "attitude": "liberal", "transiency": "neverThoughtAboutIt", "group": "A", "education": "someHighSchool", "occupation": "unskilledDomesticPersonalService"}, "_420": {"attitudeOfFriend": "NA", "attitude": "NA", "transiency": "permanent", "group": "A", "education": "gradeSchoolOrLess", "occupation": "unskilledDomesticPersonalService"}, "_180": {"attitudeOfFriend": "liberalFriend", "attitude": "ambivalent", "transiency": "NA", "group": "B", "education": "someHighSchool", "occupation": "unskilledDomesticPersonalService"}, "_181": {"attitudeOfFriend": "NA", "attitude": "NA", "transiency": "asLongAsEligible", "group": "B", "education": "highSchoolGraduate", "occupation": "whiteColorSkilled"}, "_182": {"attitudeOfFriend": "ambivalentFriend", "attitude": "liberal", "transiency": "asLongAsEligible", "group": "A", "education": "someHighSchool", "occupation": "whiteColorSkilled"}, "_183": {"attitudeOfFriend": "NA", "attitude": "NA", "transiency": "asLongAsEligible", "group": "A", "education": "gradeSchoolOrLess", "occupation": "unskilledDomesticPersonalService"}, "_184": {"attitudeOfFriend": "NA", "attitude": "NA", "transiency": "NA", "group": "A", "education": "NA", "occupation": "NA"}, "_185": {"attitudeOfFriend": "liberalFriend", "attitude": "ambivalent", "transiency": "neverThoughtAboutIt", "group": "A", "education": "gradeSchoolOrLess", "occupation": "unskilledDomesticPersonalService"}, "_186": {"attitudeOfFriend": "liberalFriend", "attitude": "liberal", "transiency": "asLongAsEligible", "group": "A", "education": "someHighSchool", "occupation": "semiSkilled"}, "_187": {"attitudeOfFriend": "NA", "attitude": "NA", "transiency": "NA", "group": "B", "education": "NA", "occupation": "NA"}, "_188": {"attitudeOfFriend": "liberalFriend", "attitude": "liberal", "transiency": "untilBetterPlace", "group": "A", "education": "NA", "occupation": "NA"}, "_189": {"attitudeOfFriend": "liberalFriend", "attitude": "liberal", "transiency": "asLongAsEligible", "group": "B", "education": "someHighSchool", "occupation": "unskilledDomesticPersonalService"}, "_380": {"attitudeOfFriend": "ambivalentFriend", "attitude": "liberal", "transiency": "asLongAsEligible", "group": "B", "education": "someHighSchool", "occupation": "unskilledDomesticPersonalService"}, "_492": {"attitudeOfFriend": "NA", "attitude": "NA", "transiency": "untilBetterPlace", "group": "A", "education": "NA", "occupation": "NA"}, "_493": {"attitudeOfFriend": "liberalFriend", "attitude": "liberal", "transiency": "asLongAsEligible", "group": "A", "education": "NA", "occupation": "NA"}, "_490": {"attitudeOfFriend": "liberalFriend", "attitude": "ambivalent", "transiency": "permanent", "group": "A", "education": "someHighSchool", "occupation": "unskilledDomesticPersonalService"}, "_491": {"attitudeOfFriend": "NA", "attitude": "NA", "transiency": "asLongAsEligible", "group": "B", "education": "NA", "occupation": "NA"}, "_496": {"attitudeOfFriend": "liberalFriend", "attitude": "liberal", "transiency": "NA", "group": "A", "education": "NA", "occupation": "NA"}, "_497": {"attitudeOfFriend": "liberalFriend", "attitude": "liberal", "transiency": "NA", "group": "B", "education": "someHighSchool", "occupation": "unskilledDomesticPersonalService"}, "_494": {"attitudeOfFriend": "NA", "attitude": "NA", "transiency": "asLongAsEligible", "group": "B", "education": "someHighSchool", "occupation": "unskilledDomesticPersonalService"}, "_495": {"attitudeOfFriend": "NA", "attitude": "NA", "transiency": "asLongAsEligible", "group": "A", "education": "gradeSchoolOrLess", "occupation": "unskilledDomesticPersonalService"}, "_498": {"attitudeOfFriend": "liberalFriend", "attitude": "liberal", "transiency": "untilOwnHome", "group": "B", "education": "highSchoolGraduate", "occupation": "unskilledDomesticPersonalService"}, "_499": {"attitudeOfFriend": "liberalFriend", "attitude": "liberal", "transiency": "permanent", "group": "B", "education": "gradeSchoolOrLess", "occupation": "unskilledDomesticPersonalService"}, "_360": {"attitudeOfFriend": "NA", "attitude": "NA", "transiency": "asLongAsEligible", "group": "A", "education": "someHighSchool", "occupation": "unskilledDomesticPersonalService"}, "_361": {"attitudeOfFriend": "NA", "attitude": "NA", "transiency": "asLongAsEligible", "group": "A", "education": "NA", "occupation": "NA"}, "_052": {"attitudeOfFriend": "liberalFriend", "attitude": "liberal", "transiency": "NA", "group": "B", "education": "gradeSchoolOrLess", "occupation": "unskilledDomesticPersonalService"}, "_053": {"attitudeOfFriend": "liberalFriend", "attitude": "liberal", "transiency": "untilBetterPlace", "group": "A", "education": "NA", "occupation": "NA"}, "_050": {"attitudeOfFriend": "liberalFriend", "attitude": "liberal", "transiency": "asLongAsEligible", "group": "A", "education": "NA", "occupation": "NA"}, "_051": {"attitudeOfFriend": "liberalFriend", "attitude": "liberal", "transiency": "asLongAsEligible", "group": "A", "education": "gradeSchoolOrLess", "occupation": "whiteColorSkilled"}, "_056": {"attitudeOfFriend": "liberalFriend", "attitude": "liberal", "transiency": "asLongAsEligible", "group": "B", "education": "gradeSchoolOrLess", "occupation": "unskilledDomesticPersonalService"}, "_057": {"attitudeOfFriend": "NA", "attitude": "NA", "transiency": "NA", "group": "A", "education": "NA", "occupation": "NA"}, "_054": {"attitudeOfFriend": "ambivalentFriend", "attitude": "ambivalent", "transiency": "asLongAsEligible", "group": "A", "education": "someHighSchool", "occupation": "unskilledDomesticPersonalService"}, "_055": {"attitudeOfFriend": "NA", "attitude": "NA", "transiency": "asLongAsEligible", "group": "B", "education": "someHighSchool", "occupation": "semiSkilled"}, "_113": {"attitudeOfFriend": "liberalFriend", "attitude": "liberal", "transiency": "permanent", "group": "B", "education": "NA", "occupation": "NA"}, "_112": {"attitudeOfFriend": "liberalFriend", "attitude": "liberal", "transiency": "NA", "group": "A", "education": "gradeSchoolOrLess", "occupation": "unskilledDomesticPersonalService"}, "_058": {"attitudeOfFriend": "liberalFriend", "attitude": "liberal", "transiency": "untilOwnHome", "group": "A", "education": "NA", "occupation": "NA"}, "_110": {"attitudeOfFriend": "ambivalentFriend", "attitude": "liberal", "transiency": "NA", "group": "B", "education": "gradeSchoolOrLess", "occupation": "unskilledDomesticPersonalService"}, "_117": {"attitudeOfFriend": "liberalFriend", "attitude": "liberal", "transiency": "neverThoughtAboutIt", "group": "B", "education": "NA", "occupation": "NA"}, "_116": {"attitudeOfFriend": "NA", "attitude": "NA", "transiency": "NA", "group": "B", "education": "NA", "occupation": "NA"}, "_115": {"attitudeOfFriend": "liberalFriend", "attitude": "liberal", "transiency": "neverThoughtAboutIt", "group": "A", "education": "someHighSchool", "occupation": "unskilledDomesticPersonalService"}, "_114": {"attitudeOfFriend": "NA", "attitude": "NA", "transiency": "NA", "group": "B", "education": "NA", "occupation": "NA"}, "_368": {"attitudeOfFriend": "NA", "attitude": "NA", "transiency": "untilBetterPlace", "group": "A", "education": "NA", "occupation": "NA"}, "_369": {"attitudeOfFriend": "NA", "attitude": "NA", "transiency": "asLongAsEligible", "group": "A", "education": "gradeSchoolOrLess", "occupation": "unskilledDomesticPersonalService"}, "_359": {"attitudeOfFriend": "liberalFriend", "attitude": "liberal", "transiency": "NA", "group": "A", "education": "gradeSchoolOrLess", "occupation": "unskilledDomesticPersonalService"}, "_238": {"attitudeOfFriend": "NA", "attitude": "NA", "transiency": "asLongAsEligible", "group": "A", "education": "gradeSchoolOrLess", "occupation": "unskilledDomesticPersonalService"}, "_239": {"attitudeOfFriend": "NA", "attitude": "NA", "transiency": "untilBetterPlace", "group": "B", "education": "gradeSchoolOrLess", "occupation": "unskilledDomesticPersonalService"}, "_236": {"attitudeOfFriend": "NA", "attitude": "NA", "transiency": "neverThoughtAboutIt", "group": "A", "education": "someHighSchool", "occupation": "semiSkilled"}, "_237": {"attitudeOfFriend": "NA", "attitude": "NA", "transiency": "permanent", "group": "A", "education": "gradeSchoolOrLess", "occupation": "unskilledDomesticPersonalService"}, "_234": {"attitudeOfFriend": "liberalFriend", "attitude": "liberal", "transiency": "asLongAsEligible", "group": "A", "education": "gradeSchoolOrLess", "occupation": "unskilledDomesticPersonalService"}, "_235": {"attitudeOfFriend": "NA", "attitude": "NA", "transiency": "NA", "group": "A", "education": "gradeSchoolOrLess", "occupation": "semiSkilled"}, "_232": {"attitudeOfFriend": "liberalFriend", "attitude": "liberal", "transiency": "asLongAsEligible", "group": "B", "education": "highSchoolGraduate", "occupation": "unskilledDomesticPersonalService"}, "_233": {"attitudeOfFriend": "liberalFriend", "attitude": "liberal", "transiency": "untilOwnHome", "group": "A", "education": "gradeSchoolOrLess", "occupation": "semiSkilled"}, "_230": {"attitudeOfFriend": "liberalFriend", "attitude": "ambivalent", "transiency": "asLongAsEligible", "group": "A", "education": "highSchoolGraduate", "occupation": "semiSkilled"}, "_231": {"attitudeOfFriend": "liberalFriend", "attitude": "liberal", "transiency": "NA", "group": "A", "education": "gradeSchoolOrLess", "occupation": "unskilledDomesticPersonalService"}, "_463": {"attitudeOfFriend": "liberalFriend", "attitude": "liberal", "transiency": "NA", "group": "A", "education": "highSchoolGraduate", "occupation": "whiteColorSkilled"}, "_462": {"attitudeOfFriend": "NA", "attitude": "NA", "transiency": "untilOwnHome", "group": "A", "education": "someHighSchool", "occupation": "unskilledDomesticPersonalService"}, "_461": {"attitudeOfFriend": "NA", "attitude": "NA", "transiency": "permanent", "group": "A", "education": "gradeSchoolOrLess", "occupation": "whiteColorSkilled"}, "_460": {"attitudeOfFriend": "NA", "attitude": "NA", "transiency": "asLongAsEligible", "group": "A", "education": "someHighSchool", "occupation": "unskilledDomesticPersonalService"}, "_467": {"attitudeOfFriend": "NA", "attitude": "NA", "transiency": "NA", "group": "B", "education": "NA", "occupation": "NA"}, "_466": {"attitudeOfFriend": "NA", "attitude": "NA", "transiency": "NA", "group": "B", "education": "someHighSchool", "occupation": "semiSkilled"}, "_465": {"attitudeOfFriend": "liberalFriend", "attitude": "liberal", "transiency": "asLongAsEligible", "group": "A", "education": "NA", "occupation": "NA"}, "_464": {"attitudeOfFriend": "liberalFriend", "attitude": "ambivalent", "transiency": "asLongAsEligible", "group": "A", "education": "highSchoolGraduate", "occupation": "unskilledDomesticPersonalService"}, "_469": {"attitudeOfFriend": "liberalFriend", "attitude": "liberal", "transiency": "neverThoughtAboutIt", "group": "A", "education": "highSchoolGraduate", "occupation": "unskilledDomesticPersonalService"}, "_468": {"attitudeOfFriend": "liberalFriend", "attitude": "liberal", "transiency": "untilBetterPlace", "group": "A", "education": "NA", "occupation": "NA"}, "_351": {"attitudeOfFriend": "NA", "attitude": "NA", "transiency": "asLongAsEligible", "group": "B", "education": "NA", "occupation": "NA"}, "_350": {"attitudeOfFriend": "liberalFriend", "attitude": "liberal", "transiency": "NA", "group": "A", "education": "someHighSchool", "occupation": "semiSkilled"}, "_308": {"attitudeOfFriend": "NA", "attitude": "NA", "transiency": "permanent", "group": "B", "education": "NA", "occupation": "NA"}, "_309": {"attitudeOfFriend": "liberalFriend", "attitude": "ambivalent", "transiency": "asLongAsEligible", "group": "A", "education": "someHighSchool", "occupation": "whiteColorSkilled"}, "_302": {"attitudeOfFriend": "liberalFriend", "attitude": "liberal", "transiency": "asLongAsEligible", "group": "A", "education": "NA", "occupation": "NA"}, "_303": {"attitudeOfFriend": "NA", "attitude": "NA", "transiency": "NA", "group": "B", "education": "NA", "occupation": "NA"}, "_300": {"attitudeOfFriend": "NA", "attitude": "NA", "transiency": "asLongAsEligible", "group": "A", "education": "NA", "occupation": "NA"}, "_301": {"attitudeOfFriend": "NA", "attitude": "NA", "transiency": "asLongAsEligible", "group": "B", "education": "gradeSchoolOrLess", "occupation": "unskilledDomesticPersonalService"}, "_306": {"attitudeOfFriend": "ambivalentFriend", "attitude": "liberal", "transiency": "NA", "group": "B", "education": "highSchoolGraduate", "occupation": "unskilledDomesticPersonalService"}, "_307": {"attitudeOfFriend": "liberalFriend", "attitude": "liberal", "transiency": "permanent", "group": "A", "education": "gradeSchoolOrLess", "occupation": "unskilledDomesticPersonalService"}, "_304": {"attitudeOfFriend": "liberalFriend", "attitude": "liberal", "transiency": "NA", "group": "A", "education": "gradeSchoolOrLess", "occupation": "unskilledDomesticPersonalService"}, "_305": {"attitudeOfFriend": "NA", "attitude": "NA", "transiency": "asLongAsEligible", "group": "B", "education": "highSchoolGraduate", "occupation": "semiSkilled"}, "_389": {"attitudeOfFriend": "liberalFriend", "attitude": "liberal", "transiency": "neverThoughtAboutIt", "group": "B", "education": "NA", "occupation": "NA"}, "_400": {"attitudeOfFriend": "liberalFriend", "attitude": "liberal", "transiency": "NA", "group": "A", "education": "gradeSchoolOrLess", "occupation": "unskilledDomesticPersonalService"}, "_016": {"attitudeOfFriend": "NA", "attitude": "NA", "transiency": "NA", "group": "B", "education": "NA", "occupation": "NA"}, "_017": {"attitudeOfFriend": "liberalFriend", "attitude": "liberal", "transiency": "NA", "group": "B", "education": "someHighSchool", "occupation": "semiSkilled"}, "_014": {"attitudeOfFriend": "NA", "attitude": "NA", "transiency": "untilBetterPlace", "group": "B", "education": "NA", "occupation": "NA"}, "_015": {"attitudeOfFriend": "ambivalentFriend", "attitude": "liberal", "transiency": "NA", "group": "A", "education": "someHighSchool", "occupation": "unskilledDomesticPersonalService"}, "_012": {"attitudeOfFriend": "liberalFriend", "attitude": "liberal", "transiency": "neverThoughtAboutIt", "group": "B", "education": "someHighSchool", "occupation": "semiSkilled"}, "_013": {"attitudeOfFriend": "NA", "attitude": "NA", "transiency": "neverThoughtAboutIt", "group": "B", "education": "gradeSchoolOrLess", "occupation": "unskilledDomesticPersonalService"}, "_010": {"attitudeOfFriend": "liberalFriend", "attitude": "liberal", "transiency": "untilBetterPlace", "group": "B", "education": "someHighSchool", "occupation": "whiteColorSkilled"}, "_011": {"attitudeOfFriend": "liberalFriend", "attitude": "liberal", "transiency": "NA", "group": "B", "education": "NA", "occupation": "NA"}, "_018": {"attitudeOfFriend": "NA", "attitude": "NA", "transiency": "NA", "group": "B", "education": "highSchoolGraduate", "occupation": "unskilledDomesticPersonalService"}, "_019": {"attitudeOfFriend": "ambivalentFriend", "attitude": "liberal", "transiency": "NA", "group": "B", "education": "NA", "occupation": "NA"}, "_399": {"attitudeOfFriend": "NA", "attitude": "NA", "transiency": "untilOwnHome", "group": "B", "education": "NA", "occupation": "NA"}, "_398": {"attitudeOfFriend": "liberalFriend", "attitude": "liberal", "transiency": "NA", "group": "B", "education": "NA", "occupation": "NA"}, "_395": {"attitudeOfFriend": "NA", "attitude": "NA", "transiency": "NA", "group": "B", "education": "highSchoolGraduate", "occupation": "unskilledDomesticPersonalService"}, "_394": {"attitudeOfFriend": "NA", "attitude": "NA", "transiency": "permanent", "group": "B", "education": "someHighSchool", "occupation": "whiteColorSkilled"}, "_397": {"attitudeOfFriend": "NA", "attitude": "NA", "transiency": "NA", "group": "A", "education": "gradeSchoolOrLess", "occupation": "semiSkilled"}, "_396": {"attitudeOfFriend": "liberalFriend", "attitude": "ambivalent", "transiency": "neverThoughtAboutIt", "group": "A", "education": "someHighSchool", "occupation": "semiSkilled"}, "_391": {"attitudeOfFriend": "liberalFriend", "attitude": "liberal", "transiency": "asLongAsEligible", "group": "A", "education": "gradeSchoolOrLess", "occupation": "unskilledDomesticPersonalService"}, "_390": {"attitudeOfFriend": "ambivalentFriend", "attitude": "ambivalent", "transiency": "permanent", "group": "A", "education": "someHighSchool", "occupation": "unskilledDomesticPersonalService"}, "_393": {"attitudeOfFriend": "NA", "attitude": "NA", "transiency": "asLongAsEligible", "group": "A", "education": "gradeSchoolOrLess", "occupation": "semiSkilled"}, "_392": {"attitudeOfFriend": "liberalFriend", "attitude": "liberal", "transiency": "untilBetterPlace", "group": "A", "education": "someHighSchool", "occupation": "unskilledDomesticPersonalService"}, "_119": {"attitudeOfFriend": "NA", "attitude": "NA", "transiency": "permanent", "group": "A", "education": "gradeSchoolOrLess", "occupation": "unskilledDomesticPersonalService"}, "_118": {"attitudeOfFriend": "NA", "attitude": "NA", "transiency": "NA", "group": "B", "education": "someHighSchool", "occupation": "semiSkilled"}, "_162": {"attitudeOfFriend": "NA", "attitude": "NA", "transiency": "NA", "group": "A", "education": "gradeSchoolOrLess", "occupation": "unskilledDomesticPersonalService"}, "_163": {"attitudeOfFriend": "NA", "attitude": "NA", "transiency": "neverThoughtAboutIt", "group": "A", "education": "someHighSchool", "occupation": "unskilledDomesticPersonalService"}, "_160": {"attitudeOfFriend": "NA", "attitude": "NA", "transiency": "asLongAsEligible", "group": "B", "education": "gradeSchoolOrLess", "occupation": "semiSkilled"}, "_161": {"attitudeOfFriend": "liberalFriend", "attitude": "liberal", "transiency": "untilBetterPlace", "group": "B", "education": "NA", "occupation": "NA"}, "_166": {"attitudeOfFriend": "NA", "attitude": "NA", "transiency": "NA", "group": "B", "education": "NA", "occupation": "NA"}, "_167": {"attitudeOfFriend": "NA", "attitude": "NA", "transiency": "asLongAsEligible", "group": "B", "education": "highSchoolGraduate", "occupation": "unskilledDomesticPersonalService"}, "_164": {"attitudeOfFriend": "NA", "attitude": "NA", "transiency": "NA", "group": "B", "education": "NA", "occupation": "NA"}, "_165": {"attitudeOfFriend": "NA", "attitude": "NA", "transiency": "NA", "group": "A", "education": "gradeSchoolOrLess", "occupation": "unskilledDomesticPersonalService"}, "_168": {"attitudeOfFriend": "liberalFriend", "attitude": "liberal", "transiency": "asLongAsEligible", "group": "A", "education": "highSchoolGraduate", "occupation": "whiteColorSkilled"}, "_169": {"attitudeOfFriend": "NA", "attitude": "NA", "transiency": "permanent", "group": "B", "education": "NA", "occupation": "NA"}, "_111": {"attitudeOfFriend": "ambivalentFriend", "attitude": "ambivalent", "transiency": "asLongAsEligible", "group": "B", "education": "gradeSchoolOrLess", "occupation": "unskilledDomesticPersonalService"}}